{
  "username": "15523752009",
  "password": "021215",
  "nickname": "biscuit",
  "gender": "男",
  "avatar": "",
  "createdAt": 1772879253990,
  "partnerUsername": "17723206683",
  "loveStartDate": "2016-12-25",
  "partnerBirthday": {
    "type": "lunar",
    "solar": "2002-12-15",
    "lunar": {
      "year": 2002,
      "month": 12,
      "day": 15,
      "isLeap": false
    }
  },
  "todayMood": {
    "key": "sweet",
    "label": "撒娇",
    "icon": "🥰"
  },
  "diaries": [],
  "wishlist": [],
  "punchRecords": {},
  "lotteryOptions": [],
  "lotteryHistory": []
}